[
  {
    "Market": "Europe50",
    "Benchmark": "EZU",
    "Number of Tickers": 47,
    "Strategy CAGR": 0.28297663365754144,
    "Hedged CAGR": 0.2516393719439223,
    "Strategy MaxDD": -0.14384152745679646,
    "Hedged MaxDD": -0.13642920942479986,
    "Strategy Sharpe Ratio": 1.424050945568345,
    "Hedged Sharpe Ratio": 1.350045681583749,
    "Bench Cagr": 0.21528661725047082,
    "Bench_MaxDD": -0.12361674751081564,
    "Bench Sharpe": 1.2129918195674778,
    "Information Ratio": 0.35080188310242555,
    "Hedged Information Ratio": 0.17974302757375876,
    "PDF_Output": "",
    "Summary_Chart": "G:\\Il mio Drive\\TradingAlgoMosaic_Dev\\output\\_summary_charts\\Europe50\\summary_Europe50.png",
    "Capital Invested": 1.0,
    "Benchmark Hedge Short": 0.0952548585558125,
    "Benchmark Hedge Ticker": "EZU",
    "Hedge Portfolio Score": 90.47451414441875,
    "Last Weekly Selection": [
      {
        "Ticker": "NOKIA.HE",
        "Name": "Nokia Corporation",
        "Sector": "Technology",
        "Industry": "Communication Equipment"
      },
      {
        "Ticker": "ASML.AS",
        "Name": "ASML HOLDING",
        "Sector": "Technology",
        "Industry": "Semiconductor Equipment & Materials"
      },
      {
        "Ticker": "ENI.MI",
        "Name": "ENI",
        "Sector": "Energy",
        "Industry": "Oil & Gas Integrated"
      },
      {
        "Ticker": "ENGI.PA",
        "Name": "ENGIE",
        "Sector": "Utilities",
        "Industry": "Utilities - Diversified"
      },
      {
        "Ticker": "IFX.DE",
        "Name": "INFINEON TECHNOLOGIES AG      N",
        "Sector": "Technology",
        "Industry": "Semiconductors"
      }
    ],
    "Added Tickers": "-",
    "Removed Tickers": "-",
    "Selection Drivers": "NOKIA.HE: trend slope 0.02, stability R2 0.87, score 0.02 and passed correlation filter<br/>ASML.AS: trend slope 0.02, stability R2 0.93, score 0.02 and passed correlation filter<br/>ENI.MI: trend slope 0.01, stability R2 0.89, score 0.01 and passed correlation filter<br/>ENGI.PA: trend slope 0.01, stability R2 0.88, score 0.01 and passed correlation filter<br/>IFX.DE: trend slope 0.01, stability R2 0.63, score 0.01 and passed correlation filter",
    "Profit_Contributors": [
      {
        "Ticker": "NOKIA.HE",
        "Contribution": 0.181980383022978
      },
      {
        "Ticker": "UCG.MI",
        "Contribution": 0.15921531344764217
      },
      {
        "Ticker": "SAP.DE",
        "Contribution": 0.1418144527154498
      },
      {
        "Ticker": "ASML.AS",
        "Contribution": 0.08649715733462982
      },
      {
        "Ticker": "ENGI.PA",
        "Contribution": 0.08503530503627765
      },
      {
        "Ticker": "ENI.MI",
        "Contribution": 0.0809368704840773
      },
      {
        "Ticker": "BAYN.DE",
        "Contribution": 0.07278710510530434
      },
      {
        "Ticker": "ADYEN.AS",
        "Contribution": 0.049667290675248214
      },
      {
        "Ticker": "BBVA.MC",
        "Contribution": 0.040266588366267037
      },
      {
        "Ticker": "VNA.DE",
        "Contribution": 0.03426552801598346
      },
      {
        "Ticker": "NOVO-B.CO",
        "Contribution": 0.027333193201605134
      },
      {
        "Ticker": "ISP.MI",
        "Contribution": 0.02460282508846224
      },
      {
        "Ticker": "MUV2.DE",
        "Contribution": 0.020375944942804276
      },
      {
        "Ticker": "DTE.DE",
        "Contribution": 0.016809384191756108
      },
      {
        "Ticker": "IBE.MC",
        "Contribution": 0.01614262287416515
      },
      {
        "Ticker": "DB1.DE",
        "Contribution": 0.014299014455744424
      },
      {
        "Ticker": "AIR.PA",
        "Contribution": 0.012615150343778034
      },
      {
        "Ticker": "INGA.AS",
        "Contribution": 0.010867538935231982
      },
      {
        "Ticker": "IFX.DE",
        "Contribution": 0.009076212936944328
      },
      {
        "Ticker": "AD.AS",
        "Contribution": 0.005392813303757141
      },
      {
        "Ticker": "ABI.BR",
        "Contribution": 0.0
      },
      {
        "Ticker": "BNP.PA",
        "Contribution": 0.0
      },
      {
        "Ticker": "AI.PA",
        "Contribution": 0.0
      },
      {
        "Ticker": "VOW3.DE",
        "Contribution": 0.0
      },
      {
        "Ticker": "DG.PA",
        "Contribution": 0.0
      },
      {
        "Ticker": "BAS.DE",
        "Contribution": 0.0
      },
      {
        "Ticker": "CS.PA",
        "Contribution": 0.0
      },
      {
        "Ticker": "NDA-FI.HE",
        "Contribution": 0.0
      },
      {
        "Ticker": "MC.PA",
        "Contribution": 0.0
      },
      {
        "Ticker": "BMW.DE",
        "Contribution": 0.0
      },
      {
        "Ticker": "LIN.DE",
        "Contribution": 0.0
      },
      {
        "Ticker": "SIE.DE",
        "Contribution": 0.0
      },
      {
        "Ticker": "SHEL.L",
        "Contribution": 0.0
      },
      {
        "Ticker": "RMS.PA",
        "Contribution": 0.0
      },
      {
        "Ticker": "RI.PA",
        "Contribution": 0.0
      },
      {
        "Ticker": "SAN.PA",
        "Contribution": 0.0
      },
      {
        "Ticker": "TTE.PA",
        "Contribution": 0.0
      },
      {
        "Ticker": "SU.PA",
        "Contribution": -0.001994082329251648
      },
      {
        "Ticker": "ALV.DE",
        "Contribution": -0.004228621592533427
      },
      {
        "Ticker": "KER.PA",
        "Contribution": -0.00525644574573951
      },
      {
        "Ticker": "ENEL.MI",
        "Contribution": -0.005930954911712312
      },
      {
        "Ticker": "STLAM.MI",
        "Contribution": -0.009897569865305843
      },
      {
        "Ticker": "PHIA.AS",
        "Contribution": -0.01789671121642287
      },
      {
        "Ticker": "OR.PA",
        "Contribution": -0.019292683747539133
      },
      {
        "Ticker": "VIV.PA",
        "Contribution": -0.03368207653474919
      },
      {
        "Ticker": "PRX.AS",
        "Contribution": -0.04731451927733401
      },
      {
        "Ticker": "FLTR.L",
        "Contribution": -0.04910464606857603
      }
    ],
    "Strategy_Returns": {
      "2024-01-12": 0.008100558950974168,
      "2024-01-19": 0.012159788381170378,
      "2024-01-26": 0.01665866393753257,
      "2024-02-02": 0.0328155385571387,
      "2024-02-09": 0.05262087603935184,
      "2024-02-16": 0.014681158165107844,
      "2024-02-23": 0.020995775948593254,
      "2024-03-01": 0.005271830907075836,
      "2024-03-08": 0.0281623253956369,
      "2024-03-15": -0.0036775479825046364,
      "2024-03-22": 0.04119528577771203,
      "2024-03-29": 0.009138284637944638,
      "2024-04-05": -0.03747820435795546,
      "2024-04-12": -0.013678282812742415,
      "2024-04-19": 0.007310651471784002,
      "2024-04-26": 0.04061190935587877,
      "2024-05-03": -0.04259688134804529,
      "2024-05-10": 0.026542860632183807,
      "2024-05-17": 0.031265786027313114,
      "2024-05-24": -0.005070240952592897,
      "2024-05-31": -0.008677331194791749,
      "2024-06-07": 0.010936455468584017,
      "2024-06-14": -0.0466023664977655,
      "2024-06-21": 0.01488498357153123,
      "2024-06-28": 0.016949473445597274,
      "2024-07-05": 0.02302159546746574,
      "2024-07-12": 0.02139490187787474,
      "2024-07-19": -0.06431142383671162,
      "2024-07-26": -0.010874511031486622,
      "2024-08-02": -0.07493672846484001,
      "2024-08-09": 0.015295124390374504,
      "2024-08-16": 0.07050149674026507,
      "2024-08-23": 0.00819670423129959,
      "2024-08-30": 0.020841614480794135,
      "2024-09-06": -0.0294239275235334,
      "2024-09-13": 0.029415620344313442,
      "2024-09-20": -0.006061145554663194,
      "2024-09-27": 0.01506127791699119,
      "2024-10-04": -0.0154893042528782,
      "2024-10-11": 0.03136959018919483,
      "2024-10-18": 0.030949061514533582,
      "2024-10-25": 0.01062448243495595,
      "2024-11-01": -0.02854475217841268,
      "2024-11-08": -0.01105152769648432,
      "2024-11-15": -0.001400283512151046,
      "2024-11-22": 0.00022999137014068083,
      "2024-11-29": -0.003833276160591259,
      "2024-12-06": 0.03758325922931127,
      "2024-12-13": 0.0005985733103326396,
      "2024-12-20": -0.020218377385860742,
      "2024-12-27": 0.0032987176249084094,
      "2025-01-03": -0.005614275644286626,
      "2025-01-10": 0.00012437200020465333,
      "2025-01-17": 0.029065464592901824,
      "2025-01-24": -0.0051974565833818875,
      "2025-01-31": 0.041030363325816,
      "2025-02-07": 0.017486416358747592,
      "2025-02-14": 0.013825765858464178,
      "2025-02-21": 0.01113308970724769,
      "2025-02-28": 0.00112646691863727,
      "2025-03-07": -0.024867279808272635,
      "2025-03-14": -0.019996929392685492,
      "2025-03-21": 0.009390359554012795,
      "2025-03-28": -0.0009780845497141533,
      "2025-04-04": -0.07637483669302159,
      "2025-04-11": -0.019786795113588718,
      "2025-04-18": 0.032480978708483654,
      "2025-04-25": 0.021824090335809565,
      "2025-05-02": 0.03046317098340401,
      "2025-05-09": 0.008739922858649996,
      "2025-05-16": 0.019652406470932027,
      "2025-05-23": 0.0031921213007635174,
      "2025-05-30": -0.005163259862580816,
      "2025-06-06": 0.0075750097200197875,
      "2025-06-13": -0.032767880405803806,
      "2025-06-20": -0.009210644595475492,
      "2025-06-27": 0.012674040407202769,
      "2025-07-04": -0.0018136593559854308,
      "2025-07-11": 0.0005308309021603286,
      "2025-07-18": 0.002842749085411267,
      "2025-07-25": 0.002853828836993033,
      "2025-08-01": -0.017954685806937598,
      "2025-08-08": 0.012416825159981437,
      "2025-08-15": 0.0016880088988469044,
      "2025-08-22": -0.0008678676206439473,
      "2025-08-29": -0.03305190255838031,
      "2025-09-05": -0.01080702778472964,
      "2025-09-12": 0.01976988196207463,
      "2025-09-19": -0.015872002758727244,
      "2025-09-26": 0.005829847688817447,
      "2025-10-03": 0.01669124944783329,
      "2025-10-10": -0.005164534026395495,
      "2025-10-17": -0.014008940071955966,
      "2025-10-24": 0.00390507845176824,
      "2025-10-31": 0.010065838821007755,
      "2025-11-07": 0.01083033861945748,
      "2025-11-14": 0.04202879816913163,
      "2025-11-21": -0.023704388043156888,
      "2025-11-28": 0.0434807471840053,
      "2025-12-05": 0.006313096649405825,
      "2025-12-12": 0.02830203934068609,
      "2025-12-19": 0.013275422209155785,
      "2025-12-26": -0.004548795706736608,
      "2026-01-02": 0.03561324606818661,
      "2026-01-09": 0.008939946200163584,
      "2026-01-16": 0.023107969561176667,
      "2026-01-23": 0.00818769519441509,
      "2026-01-30": 0.01027443303916864,
      "2026-02-06": 0.0015860847657154231,
      "2026-02-13": -0.010693047756000218,
      "2026-02-20": 0.00541538599091651,
      "2026-02-27": 0.005048235598233974,
      "2026-03-06": -0.06623521662972742,
      "2026-03-13": 0.027371132795949826,
      "2026-03-20": -0.015368530639512046,
      "2026-03-27": 0.017183483066703698,
      "2026-04-03": 0.04600672206841483,
      "2026-04-10": 0.024112686351189128,
      "2026-04-17": -0.010226288519021076,
      "2026-04-24": 0.008386263546574346,
      "2026-05-01": 0.043255446160530786,
      "2026-05-08": -0.0012867280647642643,
      "2026-05-15": 0.023247712115055608,
      "2026-05-22": 0.047269538259332666,
      "2026-05-29": -0.03562360890028515,
      "2026-06-05": 0.02986666040802821,
      "2026-06-12": 0.02218215251365896,
      "2026-06-19": -0.02551496912998752
    },
    "Hedged_Strategy_Returns": {
      "2024-01-12": 0.007450432758752568,
      "2024-01-19": 0.013064742928021289,
      "2024-01-26": 0.01415096203704902,
      "2024-02-02": 0.03315542384447001,
      "2024-02-09": 0.051772140770633523,
      "2024-02-16": 0.01430233224695554,
      "2024-02-23": 0.018401072238531047,
      "2024-03-01": 0.0045949026507114965,
      "2024-03-08": 0.026891166620389484,
      "2024-03-15": -0.004157928766188146,
      "2024-03-22": 0.040819170636512636,
      "2024-03-29": 0.008332365290513621,
      "2024-04-05": -0.03669697671404637,
      "2024-04-12": -0.01058617262947581,
      "2024-04-19": 0.00776311982716793,
      "2024-04-26": 0.038453770845771285,
      "2024-05-03": -0.04256996346851172,
      "2024-05-10": 0.02336300909291178,
      "2024-05-17": 0.030150913123759837,
      "2024-05-24": -0.0045680842267001864,
      "2024-05-31": -0.00838742053220043,
      "2024-06-07": 0.011109971252990958,
      "2024-06-14": -0.04233173389942513,
      "2024-06-21": 0.013608510927100248,
      "2024-06-28": 0.017204751423836484,
      "2024-07-05": 0.019407754182661607,
      "2024-07-12": 0.01973902749041212,
      "2024-07-19": -0.060903164744821825,
      "2024-07-26": -0.011574501206179866,
      "2024-08-02": -0.06965585925654161,
      "2024-08-09": 0.014368229192710524,
      "2024-08-16": 0.06490588789214224,
      "2024-08-23": 0.0037541974906349918,
      "2024-08-30": 0.020610834735741657,
      "2024-09-06": -0.02416633286407377,
      "2024-09-13": 0.026353450574756465,
      "2024-09-20": -0.007432109383330721,
      "2024-09-27": 0.010079938697037827,
      "2024-10-04": -0.010867276444369467,
      "2024-10-11": 0.03139543776775322,
      "2024-10-18": 0.03165703841269596,
      "2024-10-25": 0.013630781395846503,
      "2024-11-01": -0.02772395053802934,
      "2024-11-08": -0.008926554119937813,
      "2024-11-15": 0.0012957242566409288,
      "2024-11-22": 0.0012113833421110165,
      "2024-11-29": -0.005845122389769752,
      "2024-12-06": 0.034190900377983224,
      "2024-12-13": 0.0014606179305742817,
      "2024-12-20": -0.017184184451407125,
      "2024-12-27": 0.0024039870287553278,
      "2025-01-03": -0.004241323056966451,
      "2025-01-10": -0.0010598389252073348,
      "2025-01-17": 0.025827752383538627,
      "2025-01-24": -0.008649231452413808,
      "2025-01-31": 0.04118989685443375,
      "2025-02-07": 0.01729039975568547,
      "2025-02-14": 0.010267465605058312,
      "2025-02-21": 0.011865108649091738,
      "2025-02-28": 0.0014290980828792765,
      "2025-03-07": -0.029628726390128923,
      "2025-03-14": -0.019255285177160686,
      "2025-03-21": 0.00987869671409869,
      "2025-03-28": 8.184279364664704e-05,
      "2025-04-04": -0.0711303778682204,
      "2025-04-11": -0.023909939338612518,
      "2025-04-18": 0.03045974826506992,
      "2025-04-25": 0.017935852396621765,
      "2025-05-02": 0.02846600836551949,
      "2025-05-09": 0.00812263633277821,
      "2025-05-16": 0.0180318815043774,
      "2025-05-23": 0.002474049014213664,
      "2025-05-30": -0.0063133795927944325,
      "2025-06-06": 0.00583633313572629,
      "2025-06-13": -0.031038775846547018,
      "2025-06-20": -0.007546997294306856,
      "2025-06-27": 0.0069495713900546985,
      "2025-07-04": -0.002680355339532814,
      "2025-07-11": 0.000329576507531959,
      "2025-07-18": 0.0045129702832200635,
      "2025-07-25": -0.001054479880095771,
      "2025-08-01": -0.011129369483303342,
      "2025-08-08": 0.0060156444112990926,
      "2025-08-15": -0.0018933566782765032,
      "2025-08-22": -0.0023761669772655036,
      "2025-08-29": -0.027906170283531262,
      "2025-09-05": -0.010304279765442015,
      "2025-09-12": 0.0164371124441256,
      "2025-09-19": -0.017578691134289892,
      "2025-09-26": 0.00479641648361584,
      "2025-10-03": 0.009820564052358316,
      "2025-10-10": 0.0025474861545629057,
      "2025-10-17": -0.019724570176359757,
      "2025-10-24": 0.0036514391866451223,
      "2025-10-31": 0.01127280745729986,
      "2025-11-07": 0.011673366416913744,
      "2025-11-14": 0.04020324052586344,
      "2025-11-21": -0.02011969170954242,
      "2025-11-28": 0.04012738407866667,
      "2025-12-05": 0.0050739209711310185,
      "2025-12-12": 0.026943212995806487,
      "2025-12-19": 0.01236211177972768,
      "2025-12-26": -0.005751663830457998,
      "2026-01-02": 0.03407346741756845,
      "2026-01-09": 0.006908588657615011,
      "2026-01-16": 0.022815207893368328,
      "2026-01-23": 0.00723425406456113,
      "2026-01-30": 0.009848808378482676,
      "2026-02-06": 0.00012762301137891896,
      "2026-02-13": -0.01073297165181697,
      "2026-02-20": 0.00281043925072888,
      "2026-02-27": 0.005210817741082341,
      "2026-03-06": -0.057970699884147714,
      "2026-03-13": 0.029228527349081546,
      "2026-03-20": -0.012071235704094962,
      "2026-03-27": 0.01706727898240712,
      "2026-04-03": 0.04047032084049551,
      "2026-04-10": 0.01744356008108583,
      "2026-04-17": -0.013064126622299388,
      "2026-04-24": 0.011232741395152068,
      "2026-05-01": 0.04296634306212277,
      "2026-05-08": -0.003191223331108106,
      "2026-05-15": 0.02627440143486215,
      "2026-05-22": 0.04403588957347848,
      "2026-05-29": -0.036766097555515076,
      "2026-06-05": 0.031573106550501384,
      "2026-06-12": 0.018607889109162556,
      "2026-06-19": -0.02641035887462595
    },
    "Benchmark_Returns": {
      "2024-01-12": 0.006692691432135023,
      "2024-01-19": -0.009007066906855266,
      "2024-01-26": 0.025752076484629516,
      "2024-02-02": -0.0035865576240229347,
      "2024-02-09": 0.008469150458482844,
      "2024-02-16": 0.0031492166896653906,
      "2024-02-23": 0.02574295574628116,
      "2024-03-01": 0.00714157433873841,
      "2024-03-08": 0.014789235992660021,
      "2024-03-15": 0.005589877129613452,
      "2024-03-22": 0.0043677717725338905,
      "2024-03-29": 0.009290399706211705,
      "2024-04-05": -0.009204882666986491,
      "2024-04-12": -0.0316268061267273,
      "2024-04-19": -0.005307279431389422,
      "2024-04-26": 0.02914021727607463,
      "2024-05-03": -0.0005982105679874783,
      "2024-05-10": 0.03451715723062132,
      "2024-05-17": 0.012343219934962901,
      "2024-05-24": -0.005715346008453026,
      "2024-05-31": -0.003257304859997645,
      "2024-06-07": -0.0019223279262310378,
      "2024-06-14": -0.048754084981882495,
      "2024-06-21": 0.01115937365401476,
      "2024-06-28": -0.0020437437762174104,
      "2024-07-05": 0.03133319325602013,
      "2024-07-12": 0.01389989394072999,
      "2024-07-19": -0.03525262243212368,
      "2024-07-26": 0.004669079768995221,
      "2024-08-02": -0.03515867246168369,
      "2024-08-09": 0.005026197734919524,
      "2024-08-16": 0.03792479967539619,
      "2024-08-23": 0.0297126948151607,
      "2024-08-30": 0.001559764303679767,
      "2024-09-06": -0.03893322380002351,
      "2024-09-13": 0.023293629201841082,
      "2024-09-20": 0.009105179431788457,
      "2024-09-27": 0.035504217257659176,
      "2024-10-04": -0.031445468320138614,
      "2024-10-11": -0.00019546243416934672,
      "2024-10-18": -0.004694853445462388,
      "2024-10-25": -0.021029756156904944,
      "2024-11-01": -0.0072277336823214355,
      "2024-11-08": -0.018402295694822546,
      "2024-11-15": -0.0228677837686605,
      "2024-11-22": -0.008222633201891316,
      "2024-11-29": 0.017431868654068206,
      "2024-12-06": 0.0292521007186346,
      "2024-12-13": -0.007917163715243869,
      "2024-12-20": -0.029105443997729186,
      "2024-12-27": 0.008911523540563238,
      "2025-01-03": -0.013459543668889462,
      "2025-01-10": 0.011937756418570755,
      "2025-01-17": 0.03328411622545535,
      "2025-01-24": 0.03302747561825403,
      "2025-01-31": -0.0019734648334031046,
      "2025-02-07": 0.0023729038412736436,
      "2025-02-14": 0.0481357993923297,
      "2025-02-21": -0.009975507437687936,
      "2025-02-28": -0.00399243444213071,
      "2025-03-07": 0.06279822321596318,
      "2025-03-14": -0.009698309560718377,
      "2025-03-21": -0.007072881752494986,
      "2025-03-28": -0.015525103271970875,
      "2025-04-04": -0.08070501733669277,
      "2025-04-11": 0.05267400769453978,
      "2025-04-18": 0.0228144638027743,
      "2025-04-25": 0.04292409443629408,
      "2025-05-02": 0.02066861581892443,
      "2025-05-09": 0.0061630233401503975,
      "2025-05-16": 0.01627575379031798,
      "2025-05-23": 0.00602717630130023,
      "2025-05-30": 0.009757127346473382,
      "2025-06-06": 0.01237493776702836,
      "2025-06-13": -0.012056303861325723,
      "2025-06-20": -0.01128379194353113,
      "2025-06-27": 0.03763347412428475,
      "2025-07-04": 0.0055668120945819854,
      "2025-07-11": 0.0011742918472998909,
      "2025-07-18": -0.009718518911669749,
      "2025-07-25": 0.020135363846304433,
      "2025-08-01": -0.046276342121144176,
      "2025-08-08": 0.03947830325838875,
      "2025-08-15": 0.02124811777386837,
      "2025-08-22": 0.007536028787707094,
      "2025-08-29": -0.02747969371250092,
      "2025-09-05": -0.002675073509955661,
      "2025-09-12": 0.015758515201534484,
      "2025-09-19": 0.007591998962197977,
      "2025-09-26": 0.0037673974039182934,
      "2025-10-03": 0.029862993630593637,
      "2025-10-10": -0.033116738472234064,
      "2025-10-17": 0.025237587336145006,
      "2025-10-24": 0.0014386272996544935,
      "2025-10-31": -0.00766167752086111,
      "2025-11-07": -0.006433974158042366,
      "2025-11-14": 0.01651292512896707,
      "2025-11-21": -0.03201148683974442,
      "2025-11-28": 0.030931207597006516,
      "2025-12-05": 0.010852254185744314,
      "2025-12-12": 0.010104203466483996,
      "2025-12-19": 0.006575046879714108,
      "2025-12-26": 0.008465284456835365,
      "2026-01-02": 0.01057049655619835,
      "2026-01-09": 0.014151606625402824,
      "2026-01-16": 0.001971740003128497,
      "2026-01-23": 0.006206535354526865,
      "2026-01-30": 0.0028585151821085564,
      "2026-02-06": 0.0103509600737699,
      "2026-02-13": 0.0002970376262265706,
      "2026-02-20": 0.019444769136810924,
      "2026-02-27": -0.0014559749078396633,
      "2026-03-06": -0.0768445657034682,
      "2026-03-13": -0.01800666405547624,
      "2026-03-20": -0.031848146621844986,
      "2026-03-27": 0.000996858592267058,
      "2026-04-03": 0.047468875325096915,
      "2026-04-10": 0.055300295089794504,
      "2026-04-17": 0.024324346070170755,
      "2026-04-24": -0.025066003910600765,
      "2026-05-01": 0.0027064013432755996,
      "2026-05-08": 0.017543777929267312,
      "2026-05-15": -0.028293521654681464,
      "2026-05-22": 0.0313921842420406,
      "2026-05-29": 0.011321885419536937,
      "2026-06-05": -0.016720044044805427,
      "2026-06-12": 0.034008600475221806,
      "2026-06-19": 0.008893871574426893
    },
    "Status_History": {
      "dates": [
        "05-01",
        "05-08",
        "05-15",
        "05-22",
        "05-29",
        "06-05",
        "06-12",
        "06-19"
      ],
      "rows": [
        {
          "Ticker": "NOKIA.HE",
          "Statuses": [
            "Selected",
            "Selected",
            "Selected",
            "Selected",
            "Selected",
            "Selected",
            "Selected",
            "Selected"
          ]
        },
        {
          "Ticker": "ASML.AS",
          "Statuses": [
            "Selected",
            "Selected",
            "Selected",
            "Selected",
            "Selected",
            "Selected",
            "Selected",
            "Selected"
          ]
        },
        {
          "Ticker": "ENI.MI",
          "Statuses": [
            "Selected",
            "Selected",
            "Selected",
            "Selected",
            "Selected",
            "Selected",
            "Selected",
            "Selected"
          ]
        },
        {
          "Ticker": "ENGI.PA",
          "Statuses": [
            "Selected",
            "Selected",
            "Selected",
            "Selected",
            "Selected",
            "Selected",
            "Selected",
            "Selected"
          ]
        },
        {
          "Ticker": "TTE.PA",
          "Statuses": [
            "Watchlist",
            "Watchlist",
            "Watchlist",
            "Watchlist",
            "Watchlist",
            "Watchlist",
            "Watchlist",
            "Watchlist"
          ]
        },
        {
          "Ticker": "IFX.DE",
          "Statuses": [
            "Watchlist",
            "Watchlist",
            "Watchlist",
            "Watchlist",
            "Watchlist",
            "Watchlist",
            "Selected",
            "Selected"
          ]
        },
        {
          "Ticker": "BAYN.DE",
          "Statuses": [
            "Selected",
            "Selected",
            "Selected",
            "Selected",
            "Selected",
            "Selected",
            "Watchlist",
            "Watchlist"
          ]
        },
        {
          "Ticker": "BBVA.MC",
          "Statuses": [
            "Watchlist",
            "Watchlist",
            "Watchlist",
            "Watchlist",
            "Watchlist",
            "Watchlist",
            "Watchlist",
            "Watchlist"
          ]
        },
        {
          "Ticker": "NDA-FI.HE",
          "Statuses": [
            "Watchlist",
            "Watchlist",
            "Watchlist",
            "Watchlist",
            "Watchlist",
            "Watchlist",
            "Watchlist",
            "Watchlist"
          ]
        },
        {
          "Ticker": "IBE.MC",
          "Statuses": [
            "Watchlist",
            "Watchlist",
            "Watchlist",
            "Watchlist",
            "Watchlist",
            "Watchlist",
            "Watchlist",
            "Watchlist"
          ]
        },
        {
          "Ticker": "ENEL.MI",
          "Statuses": [
            "Watchlist",
            "Watchlist",
            "Watchlist",
            "Watchlist",
            "Watchlist",
            "Watchlist",
            "Watchlist",
            "Watchlist"
          ]
        },
        {
          "Ticker": "INGA.AS",
          "Statuses": [
            "Watchlist",
            "Watchlist",
            "Watchlist",
            "Watchlist",
            "Watchlist",
            "Watchlist",
            "Watchlist",
            "Watchlist"
          ]
        },
        {
          "Ticker": "ABI.BR",
          "Statuses": [
            "Rejected",
            "Rejected",
            "Rejected",
            "Rejected",
            "Watchlist",
            "Watchlist",
            "Watchlist",
            "Watchlist"
          ]
        },
        {
          "Ticker": "BNP.PA",
          "Statuses": [
            "Watchlist",
            "Watchlist",
            "Watchlist",
            "Watchlist",
            "Watchlist",
            "Watchlist",
            "Watchlist",
            "Watchlist"
          ]
        },
        {
          "Ticker": "SHEL.L",
          "Statuses": [
            "Watchlist",
            "Watchlist",
            "Watchlist",
            "Watchlist",
            "Watchlist",
            "Watchlist",
            "Watchlist",
            "Watchlist"
          ]
        },
        {
          "Ticker": "BAS.DE",
          "Statuses": [
            "Watchlist",
            "Watchlist",
            "Watchlist",
            "Watchlist",
            "Watchlist",
            "Watchlist",
            "Watchlist",
            "Watchlist"
          ]
        },
        {
          "Ticker": "SU.PA",
          "Statuses": [
            "Watchlist",
            "Watchlist",
            "Watchlist",
            "Watchlist",
            "Watchlist",
            "Watchlist",
            "Watchlist",
            "Watchlist"
          ]
        },
        {
          "Ticker": "UCG.MI",
          "Statuses": [
            "Watchlist",
            "Watchlist",
            "Watchlist",
            "Watchlist",
            "Watchlist",
            "Watchlist",
            "Watchlist",
            "Watchlist"
          ]
        },
        {
          "Ticker": "ISP.MI",
          "Statuses": [
            "Watchlist",
            "Watchlist",
            "Watchlist",
            "Watchlist",
            "Watchlist",
            "Watchlist",
            "Watchlist",
            "Watchlist"
          ]
        },
        {
          "Ticker": "ALV.DE",
          "Statuses": [
            "Watchlist",
            "Watchlist",
            "Watchlist",
            "Watchlist",
            "Watchlist",
            "Watchlist",
            "Watchlist",
            "Watchlist"
          ]
        },
        {
          "Ticker": "SIE.DE",
          "Statuses": [
            "Watchlist",
            "Watchlist",
            "Watchlist",
            "Watchlist",
            "Watchlist",
            "Watchlist",
            "Watchlist",
            "Watchlist"
          ]
        },
        {
          "Ticker": "AD.AS",
          "Statuses": [
            "Watchlist",
            "Watchlist",
            "Watchlist",
            "Watchlist",
            "Watchlist",
            "Watchlist",
            "Watchlist",
            "Watchlist"
          ]
        },
        {
          "Ticker": "DG.PA",
          "Statuses": [
            "Rejected",
            "Rejected",
            "Rejected",
            "Rejected",
            "Rejected",
            "Watchlist",
            "Watchlist",
            "Watchlist"
          ]
        },
        {
          "Ticker": "LIN.DE",
          "Statuses": [
            "Rejected",
            "Rejected",
            "Rejected",
            "Rejected",
            "Rejected",
            "Rejected",
            "Rejected",
            "Rejected"
          ]
        },
        {
          "Ticker": "PHIA.AS",
          "Statuses": [
            "Watchlist",
            "Watchlist",
            "Watchlist",
            "Watchlist",
            "Watchlist",
            "Rejected",
            "Rejected",
            "Rejected"
          ]
        },
        {
          "Ticker": "KER.PA",
          "Statuses": [
            "Watchlist",
            "Watchlist",
            "Watchlist",
            "Rejected",
            "Rejected",
            "Rejected",
            "Rejected",
            "Rejected"
          ]
        },
        {
          "Ticker": "CS.PA",
          "Statuses": [
            "Rejected",
            "Rejected",
            "Rejected",
            "Rejected",
            "Rejected",
            "Rejected",
            "Rejected",
            "Rejected"
          ]
        },
        {
          "Ticker": "AI.PA",
          "Statuses": [
            "Rejected",
            "Rejected",
            "Rejected",
            "Rejected",
            "Rejected",
            "Rejected",
            "Rejected",
            "Rejected"
          ]
        },
        {
          "Ticker": "DB1.DE",
          "Statuses": [
            "Rejected",
            "Rejected",
            "Rejected",
            "Rejected",
            "Rejected",
            "Rejected",
            "Rejected",
            "Rejected"
          ]
        },
        {
          "Ticker": "OR.PA",
          "Statuses": [
            "Rejected",
            "Rejected",
            "Rejected",
            "Rejected",
            "Rejected",
            "Rejected",
            "Rejected",
            "Rejected"
          ]
        },
        {
          "Ticker": "DTE.DE",
          "Statuses": [
            "Rejected",
            "Rejected",
            "Rejected",
            "Rejected",
            "Rejected",
            "Rejected",
            "Rejected",
            "Rejected"
          ]
        },
        {
          "Ticker": "MC.PA",
          "Statuses": [
            "Rejected",
            "Rejected",
            "Rejected",
            "Rejected",
            "Rejected",
            "Rejected",
            "Rejected",
            "Rejected"
          ]
        },
        {
          "Ticker": "AIR.PA",
          "Statuses": [
            "Rejected",
            "Rejected",
            "Rejected",
            "Rejected",
            "Rejected",
            "Rejected",
            "Rejected",
            "Rejected"
          ]
        },
        {
          "Ticker": "VOW3.DE",
          "Statuses": [
            "Rejected",
            "Rejected",
            "Rejected",
            "Rejected",
            "Rejected",
            "Rejected",
            "Rejected",
            "Rejected"
          ]
        },
        {
          "Ticker": "SAN.PA",
          "Statuses": [
            "Rejected",
            "Rejected",
            "Rejected",
            "Rejected",
            "Rejected",
            "Rejected",
            "Rejected",
            "Rejected"
          ]
        },
        {
          "Ticker": "BMW.DE",
          "Statuses": [
            "Rejected",
            "Rejected",
            "Rejected",
            "Rejected",
            "Rejected",
            "Rejected",
            "Rejected",
            "Rejected"
          ]
        },
        {
          "Ticker": "MUV2.DE",
          "Statuses": [
            "Rejected",
            "Rejected",
            "Rejected",
            "Rejected",
            "Rejected",
            "Rejected",
            "Rejected",
            "Rejected"
          ]
        },
        {
          "Ticker": "STLAM.MI",
          "Statuses": [
            "Rejected",
            "Rejected",
            "Rejected",
            "Rejected",
            "Rejected",
            "Rejected",
            "Rejected",
            "Rejected"
          ]
        },
        {
          "Ticker": "PRX.AS",
          "Statuses": [
            "Rejected",
            "Rejected",
            "Rejected",
            "Rejected",
            "Rejected",
            "Rejected",
            "Rejected",
            "Rejected"
          ]
        },
        {
          "Ticker": "NOVO-B.CO",
          "Statuses": [
            "Rejected",
            "Rejected",
            "Rejected",
            "Rejected",
            "Rejected",
            "Rejected",
            "Rejected",
            "Rejected"
          ]
        },
        {
          "Ticker": "VNA.DE",
          "Statuses": [
            "Rejected",
            "Rejected",
            "Rejected",
            "Rejected",
            "Rejected",
            "Rejected",
            "Rejected",
            "Rejected"
          ]
        },
        {
          "Ticker": "RMS.PA",
          "Statuses": [
            "Rejected",
            "Rejected",
            "Rejected",
            "Rejected",
            "Rejected",
            "Rejected",
            "Rejected",
            "Rejected"
          ]
        },
        {
          "Ticker": "RI.PA",
          "Statuses": [
            "Rejected",
            "Rejected",
            "Rejected",
            "Rejected",
            "Rejected",
            "Rejected",
            "Rejected",
            "Rejected"
          ]
        },
        {
          "Ticker": "VIV.PA",
          "Statuses": [
            "Rejected",
            "Rejected",
            "Rejected",
            "Rejected",
            "Rejected",
            "Rejected",
            "Rejected",
            "Rejected"
          ]
        },
        {
          "Ticker": "ADYEN.AS",
          "Statuses": [
            "Rejected",
            "Rejected",
            "Rejected",
            "Rejected",
            "Rejected",
            "Rejected",
            "Rejected",
            "Rejected"
          ]
        },
        {
          "Ticker": "SAP.DE",
          "Statuses": [
            "Rejected",
            "Rejected",
            "Rejected",
            "Rejected",
            "Rejected",
            "Rejected",
            "Rejected",
            "Rejected"
          ]
        },
        {
          "Ticker": "FLTR.L",
          "Statuses": [
            "Rejected",
            "Rejected",
            "Rejected",
            "Rejected",
            "Rejected",
            "Rejected",
            "Rejected",
            "Rejected"
          ]
        }
      ]
    },
    "Asset_Detail_Pages": [
      "G:\\Il mio Drive\\TradingAlgoMosaic_Dev\\output\\_asset_detail_pages\\Europe50\\ADYEN_AS_asset_dashboard.png",
      "G:\\Il mio Drive\\TradingAlgoMosaic_Dev\\output\\_asset_detail_pages\\Europe50\\AD_AS_asset_dashboard.png",
      "G:\\Il mio Drive\\TradingAlgoMosaic_Dev\\output\\_asset_detail_pages\\Europe50\\AI_PA_asset_dashboard.png",
      "G:\\Il mio Drive\\TradingAlgoMosaic_Dev\\output\\_asset_detail_pages\\Europe50\\AIR_PA_asset_dashboard.png",
      "G:\\Il mio Drive\\TradingAlgoMosaic_Dev\\output\\_asset_detail_pages\\Europe50\\ALV_DE_asset_dashboard.png",
      "G:\\Il mio Drive\\TradingAlgoMosaic_Dev\\output\\_asset_detail_pages\\Europe50\\ASML_AS_asset_dashboard.png",
      "G:\\Il mio Drive\\TradingAlgoMosaic_Dev\\output\\_asset_detail_pages\\Europe50\\ABI_BR_asset_dashboard.png",
      "G:\\Il mio Drive\\TradingAlgoMosaic_Dev\\output\\_asset_detail_pages\\Europe50\\BAS_DE_asset_dashboard.png",
      "G:\\Il mio Drive\\TradingAlgoMosaic_Dev\\output\\_asset_detail_pages\\Europe50\\BAYN_DE_asset_dashboard.png",
      "G:\\Il mio Drive\\TradingAlgoMosaic_Dev\\output\\_asset_detail_pages\\Europe50\\BBVA_MC_asset_dashboard.png",
      "G:\\Il mio Drive\\TradingAlgoMosaic_Dev\\output\\_asset_detail_pages\\Europe50\\BNP_PA_asset_dashboard.png",
      "G:\\Il mio Drive\\TradingAlgoMosaic_Dev\\output\\_asset_detail_pages\\Europe50\\CS_PA_asset_dashboard.png",
      "G:\\Il mio Drive\\TradingAlgoMosaic_Dev\\output\\_asset_detail_pages\\Europe50\\DTE_DE_asset_dashboard.png",
      "G:\\Il mio Drive\\TradingAlgoMosaic_Dev\\output\\_asset_detail_pages\\Europe50\\DB1_DE_asset_dashboard.png",
      "G:\\Il mio Drive\\TradingAlgoMosaic_Dev\\output\\_asset_detail_pages\\Europe50\\DG_PA_asset_dashboard.png",
      "G:\\Il mio Drive\\TradingAlgoMosaic_Dev\\output\\_asset_detail_pages\\Europe50\\ENEL_MI_asset_dashboard.png",
      "G:\\Il mio Drive\\TradingAlgoMosaic_Dev\\output\\_asset_detail_pages\\Europe50\\ENGI_PA_asset_dashboard.png",
      "G:\\Il mio Drive\\TradingAlgoMosaic_Dev\\output\\_asset_detail_pages\\Europe50\\ENI_MI_asset_dashboard.png",
      "G:\\Il mio Drive\\TradingAlgoMosaic_Dev\\output\\_asset_detail_pages\\Europe50\\FLTR_L_asset_dashboard.png",
      "G:\\Il mio Drive\\TradingAlgoMosaic_Dev\\output\\_asset_detail_pages\\Europe50\\IBE_MC_asset_dashboard.png",
      "G:\\Il mio Drive\\TradingAlgoMosaic_Dev\\output\\_asset_detail_pages\\Europe50\\IFX_DE_asset_dashboard.png",
      "G:\\Il mio Drive\\TradingAlgoMosaic_Dev\\output\\_asset_detail_pages\\Europe50\\INGA_AS_asset_dashboard.png",
      "G:\\Il mio Drive\\TradingAlgoMosaic_Dev\\output\\_asset_detail_pages\\Europe50\\ISP_MI_asset_dashboard.png",
      "G:\\Il mio Drive\\TradingAlgoMosaic_Dev\\output\\_asset_detail_pages\\Europe50\\KER_PA_asset_dashboard.png",
      "G:\\Il mio Drive\\TradingAlgoMosaic_Dev\\output\\_asset_detail_pages\\Europe50\\LIN_DE_asset_dashboard.png",
      "G:\\Il mio Drive\\TradingAlgoMosaic_Dev\\output\\_asset_detail_pages\\Europe50\\MC_PA_asset_dashboard.png",
      "G:\\Il mio Drive\\TradingAlgoMosaic_Dev\\output\\_asset_detail_pages\\Europe50\\MUV2_DE_asset_dashboard.png",
      "G:\\Il mio Drive\\TradingAlgoMosaic_Dev\\output\\_asset_detail_pages\\Europe50\\BMW_DE_asset_dashboard.png",
      "G:\\Il mio Drive\\TradingAlgoMosaic_Dev\\output\\_asset_detail_pages\\Europe50\\NOKIA_HE_asset_dashboard.png",
      "G:\\Il mio Drive\\TradingAlgoMosaic_Dev\\output\\_asset_detail_pages\\Europe50\\NDA_FI_HE_asset_dashboard.png",
      "G:\\Il mio Drive\\TradingAlgoMosaic_Dev\\output\\_asset_detail_pages\\Europe50\\NOVO_B_CO_asset_dashboard.png",
      "G:\\Il mio Drive\\TradingAlgoMosaic_Dev\\output\\_asset_detail_pages\\Europe50\\OR_PA_asset_dashboard.png",
      "G:\\Il mio Drive\\TradingAlgoMosaic_Dev\\output\\_asset_detail_pages\\Europe50\\PHIA_AS_asset_dashboard.png",
      "G:\\Il mio Drive\\TradingAlgoMosaic_Dev\\output\\_asset_detail_pages\\Europe50\\PRX_AS_asset_dashboard.png",
      "G:\\Il mio Drive\\TradingAlgoMosaic_Dev\\output\\_asset_detail_pages\\Europe50\\RI_PA_asset_dashboard.png",
      "G:\\Il mio Drive\\TradingAlgoMosaic_Dev\\output\\_asset_detail_pages\\Europe50\\RMS_PA_asset_dashboard.png",
      "G:\\Il mio Drive\\TradingAlgoMosaic_Dev\\output\\_asset_detail_pages\\Europe50\\SAN_PA_asset_dashboard.png",
      "G:\\Il mio Drive\\TradingAlgoMosaic_Dev\\output\\_asset_detail_pages\\Europe50\\SAP_DE_asset_dashboard.png",
      "G:\\Il mio Drive\\TradingAlgoMosaic_Dev\\output\\_asset_detail_pages\\Europe50\\SIE_DE_asset_dashboard.png",
      "G:\\Il mio Drive\\TradingAlgoMosaic_Dev\\output\\_asset_detail_pages\\Europe50\\STLAM_MI_asset_dashboard.png",
      "G:\\Il mio Drive\\TradingAlgoMosaic_Dev\\output\\_asset_detail_pages\\Europe50\\SU_PA_asset_dashboard.png",
      "G:\\Il mio Drive\\TradingAlgoMosaic_Dev\\output\\_asset_detail_pages\\Europe50\\SHEL_L_asset_dashboard.png",
      "G:\\Il mio Drive\\TradingAlgoMosaic_Dev\\output\\_asset_detail_pages\\Europe50\\TTE_PA_asset_dashboard.png",
      "G:\\Il mio Drive\\TradingAlgoMosaic_Dev\\output\\_asset_detail_pages\\Europe50\\UCG_MI_asset_dashboard.png",
      "G:\\Il mio Drive\\TradingAlgoMosaic_Dev\\output\\_asset_detail_pages\\Europe50\\VOW3_DE_asset_dashboard.png",
      "G:\\Il mio Drive\\TradingAlgoMosaic_Dev\\output\\_asset_detail_pages\\Europe50\\VNA_DE_asset_dashboard.png",
      "G:\\Il mio Drive\\TradingAlgoMosaic_Dev\\output\\_asset_detail_pages\\Europe50\\VIV_PA_asset_dashboard.png"
    ],
    "Report_PDF": "",
    "Summary_PDF_Temp": "",
    "Detailed_PDF_Temp": "",
    "Status": "OK",
    "Error": ""
  }
]